gym_PBN/__init__.py
gym_PBN/types.py
gym_PBN/envs/__init__.py
gym_PBN/envs/pbcn_env.py
gym_PBN/envs/pbn_env.py
gym_PBN/envs/pbn_target.py
gym_PBN/envs/sampled_data.py
gym_PBN/envs/self_triggering.py
gym_PBN/envs/bittner/__init__.py
gym_PBN/envs/bittner/base.py
gym_PBN/envs/bittner/utils.py
gym_PBN/envs/bittner/data/genedata.xls
gym_PBN/envs/bittner/data/predictor_sets_100_5_kmeans.pkl
gym_PBN/envs/bittner/data/predictor_sets_150_5_kmeans.pkl
gym_PBN/envs/bittner/data/predictor_sets_200_5_kmeans.pkl
gym_PBN/envs/bittner/data/predictor_sets_28_15_median.pkl
gym_PBN/envs/bittner/data/predictor_sets_70_5_kmeans-log.pkl
gym_PBN/envs/bittner/data/predictor_sets_70_5_kmeans.pkl
gym_PBN/envs/bittner/gen/__init__.py
gym_PBN/envs/bittner/gen/binarise.py
gym_PBN/envs/bittner/gen/predictor_sets.py
gym_PBN/envs/common/__init__.py
gym_PBN/envs/common/node.py
gym_PBN/envs/common/pbcn.py
gym_PBN/envs/common/pbn.py
gym_PBN/utils/__init__.py
gym_PBN/utils/converters.py
gym_PBN/utils/eval.py
gym_PBN/utils/logic/__init__.py
gym_PBN/utils/logic/eval.py
gym_PBN-1.1.1.dist-info/LICENSE
gym_PBN-1.1.1.dist-info/METADATA
gym_PBN-1.1.1.dist-info/WHEEL
gym_PBN-1.1.1.dist-info/top_level.txt
gym_PBN-1.1.1.dist-info/RECORD
