Metadata-Version: 2.1
Name: gym-PBN
Version: 1.1.1
Summary: A Gymnasium environment modelling Probabilistic Boolean Networks and Probabilistic Boolean Control Networks.
Home-page: https://github.com/UoS-PLCCN/gym-PBN/
Author: Evangelos Chatzaroulas
Author-email: e.chatzaroulas@surrey.ac.uk
License: MIT
Classifier: Environment :: Console
Classifier: License :: OSI Approved :: MIT License
Classifier: Programming Language :: Python :: 3.9
Classifier: Intended Audience :: Science/Research
Classifier: Topic :: Scientific/Engineering :: Artificial Intelligence
Requires-Python: >3.9
License-File: LICENSE
Requires-Dist: gymnasium (==0.27.0)
Requires-Dist: networkx
Requires-Dist: numpy
Requires-Dist: pandas
Requires-Dist: xlrd
Requires-Dist: scipy
Requires-Dist: sklearn
Requires-Dist: numba
Requires-Dist: tqdm
Requires-Dist: psutil
Provides-Extra: dev
Requires-Dist: pytest ; extra == 'dev'
Requires-Dist: black ; extra == 'dev'
Requires-Dist: rope ; extra == 'dev'
Requires-Dist: wandb ; extra == 'dev'
Provides-Extra: vis
Requires-Dist: plotly-express (==0.4.1) ; extra == 'vis'
Requires-Dist: kaleido ; extra == 'vis'
